Metadata-Version: 2.1
Name: addstartup
Version: 1.4
Summary: a package for Add File to Windows Startup
Home-page: https://www.youtube.com/channel/UCGsKXfbCyhZoLIRukYUQyYQ
Author: MD Trackers
Author-email: mdtrackersother@gmail.com
License: MDTrack
Platform: UNKNOWN
